{"status":"success","total":{"count":7,"per_page":20},"pages":{"current":1,"all":1,"prev":null,"next":null},"prices":{"min":0,"max":0,"step":0,"curr":{"code":null,"name":null}},"data":[{"id":{"sap":19554,"api":18119554},"hash":"a4bb7d3d5395d5ed2c5daa25ca76d13b","brand":{"id":4,"name":"Nissan"},"dealer":{"id":181,"name":"\u0410\u0442\u043b\u0430\u043d\u0442-\u041c \u0411\u0430\u043b\u0442\u0438\u043a\u0430"},"model":{"name":"\u0410\u043b\u044c\u043c\u0435\u0440\u0430"},"vin":"Z8NAJL00052465037","year":2015,"mileage":49049,"img":{"10000x150":["https:\/\/api.atlantm.com\/n_files\/multifile\/462\/10000x150\/1810000019554_01.jpg"],"10000x220":["https:\/\/api.atlantm.com\/n_files\/multifile\/462\/10000x220\/1810000019554_01.jpg"],"10000x300":["https:\/\/api.atlantm.com\/n_files\/multifile\/462\/10000x300\/1810000019554_01.jpg"],"10000x440":["https:\/\/api.atlantm.com\/n_files\/multifile\/462\/10000x440\/1810000019554_01.jpg"],"original":["https:\/\/api.atlantm.com\/n_files\/multifile\/462\/1810000019554_01.jpg"]},"body":{"id":2,"name":"\u0421\u0435\u0434\u0430\u043d"},"engine":{"type":"\u0431\u0435\u043d\u0437\u0438\u043d","volume":{"full":1600,"short":1.6}},"gearbox":{"id":1,"name":"\u041c\u0435\u0445\u0430\u043d\u0438\u0447\u0435\u0441\u043a\u0430\u044f","wheel":"\u041f\u0435\u0440\u0435\u0434\u043d\u0438\u0439"},"color":{"id":13,"name":{"simple":"\u0411\u0435\u043b\u044b\u0439","official":"B2-\u0431\u0435\u043b\u044b\u0439"}},"interior":{"id":null,"name":"BU1-\u0442\u043a\u0430\u043d\u044c"},"city":{"id":2,"name":"\u0421\u0430\u043d\u043a\u0442-\u041f\u0435\u0442\u0435\u0440\u0431\u0443\u0440\u0433"},"price":{"app":409900,"rec":409900,"ust":409900,"adv":0,"online":{"standart":null,"special":null}},"manager":{"name":null,"phone":null},"text":null},{"id":{"sap":19559,"api":18119559},"hash":"0db7f5d4479fc4b8a9ab6ed740811c32","brand":{"id":1,"name":"Volkswagen"},"dealer":{"id":181,"name":"\u0410\u0442\u043b\u0430\u043d\u0442-\u041c \u0411\u0430\u043b\u0442\u0438\u043a\u0430"},"model":{"name":"Jetta"},"vin":"XW8ZZZ16ZEN903649","year":2014,"mileage":90015,"img":{"10000x150":["https:\/\/api.atlantm.com\/n_files\/multifile\/462\/10000x150\/1810000019559_01.jpg"],"10000x220":["https:\/\/api.atlantm.com\/n_files\/multifile\/462\/10000x220\/1810000019559_01.jpg"],"10000x300":["https:\/\/api.atlantm.com\/n_files\/multifile\/462\/10000x300\/1810000019559_01.jpg"],"10000x440":["https:\/\/api.atlantm.com\/n_files\/multifile\/462\/10000x440\/1810000019559_01.jpg"],"original":["https:\/\/api.atlantm.com\/n_files\/multifile\/462\/1810000019559_01.jpg"]},"body":{"id":2,"name":"\u0421\u0435\u0434\u0430\u043d"},"engine":{"type":"\u0431\u0435\u043d\u0437\u0438\u043d","volume":{"full":1390,"short":1.39}},"gearbox":{"id":4,"name":"\u0410\u0432\u0442\u043e\u043c\u0430\u0442\u0438\u0447\u0435\u0441\u043a\u0430\u044f","wheel":"\u041f\u0435\u0440\u0435\u0434\u043d\u0438\u0439"},"color":{"id":13,"name":{"simple":"\u0411\u0435\u043b\u044b\u0439","official":"B2-\u0431\u0435\u043b\u044b\u0439"}},"interior":{"id":null,"name":"BU1-\u0442\u043a\u0430\u043d\u044c"},"city":{"id":2,"name":"\u0421\u0430\u043d\u043a\u0442-\u041f\u0435\u0442\u0435\u0440\u0431\u0443\u0440\u0433"},"price":{"app":609900,"rec":609900,"ust":609900,"adv":0,"online":{"standart":null,"special":null}},"manager":{"name":null,"phone":null},"text":null},{"id":{"sap":19584,"api":18119584},"hash":"f8af797af865d155f7047bfb6c1691da","brand":{"id":1,"name":"Volkswagen"},"dealer":{"id":181,"name":"\u0410\u0442\u043b\u0430\u043d\u0442-\u041c \u0411\u0430\u043b\u0442\u0438\u043a\u0430"},"model":{"name":"Passat"},"vin":"WVWZZZ3CZEE041686","year":2013,"mileage":115500,"img":{"10000x150":["https:\/\/api.atlantm.com\/n_files\/multifile\/462\/10000x150\/1810000019584_01.jpg"],"10000x220":["https:\/\/api.atlantm.com\/n_files\/multifile\/462\/10000x220\/1810000019584_01.jpg"],"10000x300":["https:\/\/api.atlantm.com\/n_files\/multifile\/462\/10000x300\/1810000019584_01.jpg"],"10000x440":["https:\/\/api.atlantm.com\/n_files\/multifile\/462\/10000x440\/1810000019584_01.jpg"],"original":["https:\/\/api.atlantm.com\/n_files\/multifile\/462\/1810000019584_01.jpg"]},"body":{"id":2,"name":"\u0421\u0435\u0434\u0430\u043d"},"engine":{"type":"\u0431\u0435\u043d\u0437\u0438\u043d","volume":{"full":1798,"short":1.798}},"gearbox":{"id":null,"name":null,"wheel":"\u041f\u0435\u0440\u0435\u0434\u043d\u0438\u0439"},"color":{"id":289,"name":{"simple":"\u041a\u043e\u0440\u0438\u0447\u043d\u0435\u0432\u044b\u0439","official":"B8-\u043a\u043e\u0440\u0438\u0447\u043d\u0435\u0432\u044b\u0439"}},"interior":{"id":null,"name":"BU3-\u043a\u043e\u0436\u0430\/\u0442\u043a\u0430\u043d\u044c"},"city":{"id":2,"name":"\u0421\u0430\u043d\u043a\u0442-\u041f\u0435\u0442\u0435\u0440\u0431\u0443\u0440\u0433"},"price":{"app":759900,"rec":759900,"ust":759900,"adv":0,"online":{"standart":null,"special":null}},"manager":{"name":null,"phone":null},"text":null},{"id":{"sap":19547,"api":18119547},"hash":"9559957a2d0a03899177ea773d5f167c","brand":{"id":5,"name":"Renault"},"dealer":{"id":181,"name":"\u0410\u0442\u043b\u0430\u043d\u0442-\u041c \u0411\u0430\u043b\u0442\u0438\u043a\u0430"},"model":{"name":"Koleos"},"vin":"X7L8Y0C0V49488112","year":2013,"mileage":78078,"img":{"10000x150":["https:\/\/api.atlantm.com\/n_files\/multifile\/462\/10000x150\/1810000019547_01.jpg"],"10000x220":["https:\/\/api.atlantm.com\/n_files\/multifile\/462\/10000x220\/1810000019547_01.jpg"],"10000x300":["https:\/\/api.atlantm.com\/n_files\/multifile\/462\/10000x300\/1810000019547_01.jpg"],"10000x440":["https:\/\/api.atlantm.com\/n_files\/multifile\/462\/10000x440\/1810000019547_01.jpg"],"original":["https:\/\/api.atlantm.com\/n_files\/multifile\/462\/1810000019547_01.jpg"]},"body":{"id":null,"name":null},"engine":{"type":"\u0431\u0435\u043d\u0437\u0438\u043d","volume":{"full":2500,"short":2.5}},"gearbox":{"id":4,"name":"\u0410\u0432\u0442\u043e\u043c\u0430\u0442\u0438\u0447\u0435\u0441\u043a\u0430\u044f","wheel":"\u041f\u0435\u0440\u0435\u0434\u043d\u0438\u0439"},"color":{"id":13,"name":{"simple":"\u0411\u0435\u043b\u044b\u0439","official":"B2-\u0431\u0435\u043b\u044b\u0439"}},"interior":{"id":null,"name":"BU1-\u0442\u043a\u0430\u043d\u044c"},"city":{"id":2,"name":"\u0421\u0430\u043d\u043a\u0442-\u041f\u0435\u0442\u0435\u0440\u0431\u0443\u0440\u0433"},"price":{"app":779900,"rec":779900,"ust":779900,"adv":0,"online":{"standart":null,"special":null}},"manager":{"name":null,"phone":null},"text":null},{"id":{"sap":19537,"api":18119537},"hash":"00de741819504a5b054daf9e6a16e550","brand":{"id":27,"name":"BMW"},"dealer":{"id":181,"name":"\u0410\u0442\u043b\u0430\u043d\u0442-\u041c \u0411\u0430\u043b\u0442\u0438\u043a\u0430"},"model":{"name":"530 D Xdrive Gran Turismo"},"vin":"WBASP61000C754372","year":2010,"mileage":93694,"img":{"10000x150":["https:\/\/api.atlantm.com\/n_files\/multifile\/462\/10000x150\/1810000019537_01.jpg"],"10000x220":["https:\/\/api.atlantm.com\/n_files\/multifile\/462\/10000x220\/1810000019537_01.jpg"],"10000x300":["https:\/\/api.atlantm.com\/n_files\/multifile\/462\/10000x300\/1810000019537_01.jpg"],"10000x440":["https:\/\/api.atlantm.com\/n_files\/multifile\/462\/10000x440\/1810000019537_01.jpg"],"original":["https:\/\/api.atlantm.com\/n_files\/multifile\/462\/1810000019537_01.jpg"]},"body":{"id":null,"name":null},"engine":{"type":"\u0434\u0438\u0437\u0435\u043b\u044c","volume":{"full":3000,"short":3}},"gearbox":{"id":4,"name":"\u0410\u0432\u0442\u043e\u043c\u0430\u0442\u0438\u0447\u0435\u0441\u043a\u0430\u044f","wheel":"\u041f\u0435\u0440\u0435\u0434\u043d\u0438\u0439"},"color":{"id":5,"name":{"simple":"\u0427\u0435\u0440\u043d\u044b\u0439","official":"B16-\u0447\u0435\u0440\u043d\u044b\u0439"}},"interior":{"id":null,"name":"BU3-\u043a\u043e\u0436\u0430\/\u0442\u043a\u0430\u043d\u044c"},"city":{"id":2,"name":"\u0421\u0430\u043d\u043a\u0442-\u041f\u0435\u0442\u0435\u0440\u0431\u0443\u0440\u0433"},"price":{"app":1199900,"rec":1280000,"ust":1199900,"adv":0,"online":{"standart":null,"special":null}},"manager":{"name":null,"phone":null},"text":null},{"id":{"sap":19468,"api":18119468},"hash":"524838a009a0ae1f893fb87448a6fb64","brand":{"id":27,"name":"BMW"},"dealer":{"id":181,"name":"\u0410\u0442\u043b\u0430\u043d\u0442-\u041c \u0411\u0430\u043b\u0442\u0438\u043a\u0430"},"model":{"name":"530xdrive  Gran  Turismo"},"vin":"WBASP61040C756335","year":2011,"mileage":118118,"img":{"10000x150":["https:\/\/api.atlantm.com\/n_files\/multifile\/462\/10000x150\/1810000019468_01.jpg"],"10000x220":["https:\/\/api.atlantm.com\/n_files\/multifile\/462\/10000x220\/1810000019468_01.jpg"],"10000x300":["https:\/\/api.atlantm.com\/n_files\/multifile\/462\/10000x300\/1810000019468_01.jpg"],"10000x440":["https:\/\/api.atlantm.com\/n_files\/multifile\/462\/10000x440\/1810000019468_01.jpg"],"original":["https:\/\/api.atlantm.com\/n_files\/multifile\/462\/1810000019468_01.jpg"]},"body":{"id":3,"name":"\u0423\u043d\u0438\u0432\u0435\u0440\u0441\u0430\u043b"},"engine":{"type":"\u0434\u0438\u0437\u0435\u043b\u044c","volume":{"full":2993,"short":2.993}},"gearbox":{"id":4,"name":"\u0410\u0432\u0442\u043e\u043c\u0430\u0442\u0438\u0447\u0435\u0441\u043a\u0430\u044f","wheel":"\u041f\u0435\u0440\u0435\u0434\u043d\u0438\u0439"},"color":{"id":13,"name":{"simple":"\u0411\u0435\u043b\u044b\u0439","official":"B2-\u0431\u0435\u043b\u044b\u0439"}},"interior":{"id":null,"name":"BU5-\u043a\u043e\u0436\u0430"},"city":{"id":2,"name":"\u0421\u0430\u043d\u043a\u0442-\u041f\u0435\u0442\u0435\u0440\u0431\u0443\u0440\u0433"},"price":{"app":1439900,"rec":1439900,"ust":1439900,"adv":0,"online":{"standart":null,"special":null}},"manager":{"name":null,"phone":null},"text":null},{"id":{"sap":19513,"api":18119513},"hash":"3a4f4289b29b340d27bc8641533f48b1","brand":{"id":45,"name":"Hummer"},"dealer":{"id":181,"name":"\u0410\u0442\u043b\u0430\u043d\u0442-\u041c \u0411\u0430\u043b\u0442\u0438\u043a\u0430"},"model":{"name":"H2"},"vin":"5GRGN23878H108771","year":2008,"mileage":91000,"img":{"10000x150":["https:\/\/api.atlantm.com\/n_files\/multifile\/462\/10000x150\/1810000019513_01.jpg"],"10000x220":["https:\/\/api.atlantm.com\/n_files\/multifile\/462\/10000x220\/1810000019513_01.jpg"],"10000x300":["https:\/\/api.atlantm.com\/n_files\/multifile\/462\/10000x300\/1810000019513_01.jpg"],"10000x440":["https:\/\/api.atlantm.com\/n_files\/multifile\/462\/10000x440\/1810000019513_01.jpg"],"original":["https:\/\/api.atlantm.com\/n_files\/multifile\/462\/1810000019513_01.jpg"]},"body":{"id":null,"name":null},"engine":{"type":"","volume":{"full":0,"short":0}},"gearbox":{"id":null,"name":null,"wheel":"\u041f\u0435\u0440\u0435\u0434\u043d\u0438\u0439"},"color":{"id":5,"name":{"simple":"\u0427\u0435\u0440\u043d\u044b\u0439","official":"B16-\u0447\u0435\u0440\u043d\u044b\u0439"}},"interior":{"id":null,"name":"BU5-\u043a\u043e\u0436\u0430"},"city":{"id":2,"name":"\u0421\u0430\u043d\u043a\u0442-\u041f\u0435\u0442\u0435\u0440\u0431\u0443\u0440\u0433"},"price":{"app":1999900,"rec":1999900,"ust":1999900,"adv":0,"online":{"standart":null,"special":null}},"manager":{"name":null,"phone":null},"text":null}]}